tox_factor/__init__.py
tox_factor/compat.py
tox_factor/factor.py
tox_factor/hooks.py
tox_factor/test.py
tox_factor-0.1.2.dist-info/LICENSE
tox_factor-0.1.2.dist-info/METADATA
tox_factor-0.1.2.dist-info/WHEEL
tox_factor-0.1.2.dist-info/entry_points.txt
tox_factor-0.1.2.dist-info/top_level.txt
tox_factor-0.1.2.dist-info/RECORD
