Metadata-Version: 2.1
Name: tox-factor
Version: 0.1.2
Summary: Run tox testenvs that match a given factor
Home-page: https://github.com/rpkilby/tox-factor
Author: Ryan P Kilby
Author-email: kilbyr@gmail.com
License: BSD 3-Clause License
Project-URL: Source, https://github.com/rpkilby/tox-factor
Project-URL: Tracker, https://github.com/rpkilby/tox-factor/issues
Platform: UNKNOWN
Classifier: Development Status :: 3 - Alpha
Classifier: Framework :: tox
Classifier: Intended Audience :: Developers
Classifier: License :: OSI Approved :: BSD License
Classifier: Operating System :: POSIX
Classifier: Operating System :: Microsoft :: Windows
Classifier: Operating System :: MacOS :: MacOS X
Classifier: Programming Language :: Python
Classifier: Programming Language :: Python :: 2
Classifier: Programming Language :: Python :: 2.7
Classifier: Programming Language :: Python :: 3
Classifier: Programming Language :: Python :: 3.5
Classifier: Programming Language :: Python :: 3.6
Classifier: Programming Language :: Python :: 3.7
Classifier: Topic :: Software Development :: Testing
Requires-Dist: tox
